stockplot/__init__.py
stockplot/calculate_price_movement.py
stockplot/create_candlestick_plot.py
stockplot/main.py
stockplot-2.0.4.dist-info/METADATA
stockplot-2.0.4.dist-info/WHEEL
stockplot-2.0.4.dist-info/entry_points.txt
stockplot-2.0.4.dist-info/top_level.txt
stockplot-2.0.4.dist-info/RECORD
